Metadata-Version: 1.0
Name: hcy-schedule
Version: 0.0.2
Summary: 进度条
Home-page: http://google.com
Author: hcyangnull
Author-email: hcyangnull@gmail.com
License: UNKNOWN
Platform: UNKNOWN
